crow_hooks/__init__.py
crow_hooks/compilation/__init__.py
crow_hooks/compilation/artifact_manager.py
crow_hooks/compilation/compilation_manager.py
crow_hooks/config/__init__.py
crow_hooks/config/config_manager.py
crow_hooks/config/config_models.py
crow_hooks/discovery/__init__.py
crow_hooks/discovery/compiler_detector.py
crow_hooks/discovery/project_locator.py
crow_hooks/discovery/source_discoverer.py
crow_hooks/execution/__init__.py
crow_hooks/execution/build_executor.py
crow_hooks/execution/file_manager.py
crow_hooks/hooks/__init__.py
crow_hooks/hooks/hook_context.py
crow_hooks-0.1.0.dist-info/METADATA
crow_hooks-0.1.0.dist-info/WHEEL
crow_hooks-0.1.0.dist-info/licenses/LICENSE
crow_hooks-0.1.0.dist-info/RECORD
