Metadata-Version: 2.4
Name: crow-hooks
Version: 0.1.0
Summary: Hook system for the Crow build system
License: MIT
License-File: LICENSE
Author: user-with-username
Requires-Python: >=3.8,<4.0
Classifier: License :: OSI Approved :: MIT License
Classifier: Programming Language :: Python :: 3
Classifier: Programming Language :: Python :: 3.8
Classifier: Programming Language :: Python :: 3.9
Classifier: Programming Language :: Python :: 3.10
Classifier: Programming Language :: Python :: 3.11
Classifier: Programming Language :: Python :: 3.12
Classifier: Programming Language :: Python :: 3.13
Classifier: Programming Language :: Python :: 3.14
Requires-Dist: toml (>=0.10.2,<0.11.0)
